umirobot/__init__.py
umirobot/__main__.py
umirobot/_umirobot.py
umirobot/_umirobot_communication_loop.py
umirobot/gui/__init__.py
umirobot/gui/_umirobot_main_window.py
umirobot/gui/_umirobot_main_window_ui.py
umirobot/gui/icon.png
umirobot/gui/umirobot.png
umirobot/gui/umirobot_main_window.ui
umirobot/shared_memory/__init__.py
umirobot/shared_memory/test_umirobot_shared_memory.py
umirobot/shared_memory/umirobot_shared_memory_common.py
umirobot/shared_memory/umirobot_shared_memory_provider.py
umirobot/shared_memory/umirobot_shared_memory_receiver.py
umirobot-22.4.28.dist-info/LICENSE
umirobot-22.4.28.dist-info/METADATA
umirobot-22.4.28.dist-info/WHEEL
umirobot-22.4.28.dist-info/top_level.txt
umirobot-22.4.28.dist-info/RECORD
