Metadata-Version: 2.1
Name: umirobot
Version: 22.4.28
Summary: UMIRobot control code and GUI for Python.
Home-page: https://github.com/mmmarinho/umirobot-py
Author: Murilo M. Marinho
Author-email: murilo@g.ecc.u-tokyo.ac.jp
License: GPLv3
Platform: UNKNOWN
Requires-Python: >=3.8
Requires-Dist: pyserial
Requires-Dist: PyQt6
Requires-Dist: dqrobotics
